pytest_result_sender/__init__.py
pytest_result_sender/plugin.py
Sj_Django_Vue3_Pytest-0.1.2.dist-info/entry_points.txt
Sj_Django_Vue3_Pytest-0.1.2.dist-info/WHEEL
Sj_Django_Vue3_Pytest-0.1.2.dist-info/METADATA
Sj_Django_Vue3_Pytest-0.1.2.dist-info/RECORD
