Metadata-Version: 2.1
Name: Sj-Django-Vue3-Pytest
Version: 0.1.2
Summary: Default template for PDM package
Author-email: ajianbest6 <3036474507@qq.com>
Requires-Python: >=3.10
Requires-Dist: pytest>=8.4.2
